gov_scheme_mcp/__init__.py
gov_scheme_mcp/__main__.py
gov_scheme_mcp/main.py
gov_scheme_mcp/server.py
gov_scheme_mcp-0.1.3.dist-info/METADATA
gov_scheme_mcp-0.1.3.dist-info/WHEEL
gov_scheme_mcp-0.1.3.dist-info/entry_points.txt
gov_scheme_mcp-0.1.3.dist-info/licenses/LICENSE
gov_scheme_mcp-0.1.3.dist-info/RECORD
