Metadata-Version: 2.4
Name: gov-scheme-mcp
Version: 0.1.3
Summary: Model Context Protocol (MCP) server for Indian Government Schemes database
Project-URL: Homepage, https://github.com/magicstack-llp/gov-scheme-mcp-py
Project-URL: Repository, https://github.com/magicstack-llp/gov-scheme-mcp-py
Project-URL: Issues, https://github.com/magicstack-llp/gov-scheme-mcp-py/issues
Project-URL: Documentation, https://github.com/magicstack-llp/gov-scheme-mcp-py#readme
Author-email: Kuldip Satpute <satputekuldip@gmail.com>
License: MIT
License-File: LICENSE
Keywords: benefits,eligibility,government,india,mcp,schemes
Classifier: Development Status :: 4 - Beta
Classifier: Intended Audience :: Developers
Classifier: License :: OSI Approved :: MIT License
Classifier: Programming Language :: Python :: 3
Classifier: Programming Language :: Python :: 3.10
Classifier: Programming Language :: Python :: 3.11
Classifier: Programming Language :: Python :: 3.12
Classifier: Topic :: Internet :: WWW/HTTP :: Dynamic Content
Classifier: Topic :: Software Development :: Libraries :: Python Modules
Requires-Python: >=3.10
Requires-Dist: httpx>=0.28.1
Requires-Dist: mcp[cli]>=1.14.1
Provides-Extra: dev
Requires-Dist: black>=23.0.0; extra == 'dev'
Requires-Dist: flake8>=6.0.0; extra == 'dev'
Requires-Dist: isort>=5.12.0; extra == 'dev'
Requires-Dist: mypy>=1.0.0; extra == 'dev'
Requires-Dist: pytest-asyncio>=0.21.0; extra == 'dev'
Requires-Dist: pytest>=7.0.0; extra == 'dev'
